{
  "$schema": "https://developer.microsoft.com/json-schemas/fabric/item/report/definition/visualContainer/2.2.0/schema.json",
  "name": "c751a9a865b8e8aba9cd",
  "position": {
    "x": 0,
    "y": 0,
    "z": 6000,
    "height": 70,
    "width": 222.48057955834858,
    "tabOrder": 6000
  },
  "visual": {
    "visualType": "slicer",
    "query": {
      "queryState": {
        "Values": {
          "projections": [
            {
              "field": {
                "Column": {
                  "Expression": {
                    "SourceRef": {
                      "Entity": "AP Checks"
                    }
                  },
                  "Property": "Account Description"
                }
              },
              "queryRef": "AP Checks.Account Description",
              "nativeQueryRef": "Account Description",
              "active": true
            }
          ]
        }
      }
    },
    "objects": {
      "data": [
        {
          "properties": {
            "mode": {
              "expr": {
                "Literal": {
                  "Value": "'Dropdown'"
                }
              }
            }
          }
        }
      ],
      "general": [
        {
          "properties": {
            "selfFilterEnabled": {
              "expr": {
                "Literal": {
                  "Value": "true"
                }
              }
            }
          }
        }
      ],
      "selection": [
        {
          "properties": {
            "singleSelect": {
              "expr": {
                "Literal": {
                  "Value": "false"
                }
              }
            },
            "selectAllCheckboxEnabled": {
              "expr": {
                "Literal": {
                  "Value": "true"
                }
              }
            }
          }
        }
      ],
      "header": [
        {
          "properties": {
            "show": {
              "expr": {
                "Literal": {
                  "Value": "true"
                }
              }
            }
          }
        }
      ]
    },
    "visualContainerObjects": {
      "visualHeader": [
        {
          "properties": {
            "show": {
              "expr": {
                "Literal": {
                  "Value": "false"
                }
              }
            }
          }
        }
      ],
      "title": [
        {
          "properties": {
            "text": {
              "expr": {
                "Literal": {
                  "Value": "'Acct Desc'"
                }
              }
            }
          }
        }
      ]
    },
    "drillFilterOtherVisuals": true
  },
  "parentGroupName": "f5f3ab532e19129ae8e9"
}